LICENSE
MANIFEST.in
README.rst
requirements.txt
setup.cfg
setup.py
docker_squash/__init__.py
docker_squash/cli.py
docker_squash/errors.py
docker_squash/image.py
docker_squash/squash.py
docker_squash/v1_image.py
docker_squash/v2_image.py
docker_squash/version.py
docker_squash.egg-info/PKG-INFO
docker_squash.egg-info/SOURCES.txt
docker_squash.egg-info/dependency_links.txt
docker_squash.egg-info/entry_points.txt
docker_squash.egg-info/requires.txt
docker_squash.egg-info/top_level.txt
docker_squash/lib/__init__.py
docker_squash/lib/common.py
tests/test_integ_squash.py
tests/test_qa.py
tests/test_unit_squash.py
tests/test_unit_v1_image.py
tests/test_unit_v2_image.py