Metadata-Version: 2.1
Name: docker-squash
Version: 1.2.0
Summary: Docker layer squashing tool
Home-page: https://github.com/goldmann/docker-squash
Download-URL: https://github.com/goldmann/docker-squash/archive/1.2.0.tar.gz
Author: Marek Goldmann
Author-email: marek.goldmann@gmail.com
License: MIT
Keywords: docker
License-File: LICENSE
Requires-Dist: docker
Requires-Dist: packaging
